LICENSE
setup.py
WakeCommerce.egg-info/PKG-INFO
WakeCommerce.egg-info/SOURCES.txt
WakeCommerce.egg-info/dependency_links.txt
WakeCommerce.egg-info/requires.txt
WakeCommerce.egg-info/top_level.txt
get/__init__.py
get/order.py
post/__init__.py
put/__init__.py