Metadata-Version: 2.1
Name: WakeCommerce
Version: 0.0.1
Summary: WakeCommerce API Request Module
Author: Elemental (Tom Neto)
Author-email: <info@elemental.run>
Keywords: python,WakeCommerce,TrayCorp,API,Request
Classifier: Development Status :: 1 - Planning
Classifier: Intended Audience :: Developers
Classifier: Programming Language :: Python :: 3.11
Classifier: Operating System :: Unix
Classifier: Operating System :: MacOS :: MacOS X
Classifier: Operating System :: Microsoft :: Windows
License-File: LICENSE
